async_rx/__init__.py
async_rx/multicast/__init__.py
async_rx/multicast/rx_publish.py
async_rx/multicast/rx_publish_behavior.py
async_rx/multicast/rx_publish_replay.py
async_rx/observable/__init__.py
async_rx/observable/rx_amb.py
async_rx/observable/rx_avg.py
async_rx/observable/rx_buffer.py
async_rx/observable/rx_concat.py
async_rx/observable/rx_count.py
async_rx/observable/rx_create.py
async_rx/observable/rx_debounce.py
async_rx/observable/rx_defer.py
async_rx/observable/rx_delay.py
async_rx/observable/rx_dict.py
async_rx/observable/rx_distinct.py
async_rx/observable/rx_empty.py
async_rx/observable/rx_filter.py
async_rx/observable/rx_first.py
async_rx/observable/rx_forward.py
async_rx/observable/rx_from.py
async_rx/observable/rx_group_by.py
async_rx/observable/rx_last.py
async_rx/observable/rx_list.py
async_rx/observable/rx_map.py
async_rx/observable/rx_max.py
async_rx/observable/rx_merge.py
async_rx/observable/rx_merge_map.py
async_rx/observable/rx_min.py
async_rx/observable/rx_of.py
async_rx/observable/rx_range.py
async_rx/observable/rx_reduce.py
async_rx/observable/rx_repeat.py
async_rx/observable/rx_repeat_series.py
async_rx/observable/rx_sample.py
async_rx/observable/rx_skip.py
async_rx/observable/rx_sum.py
async_rx/observable/rx_take.py
async_rx/observable/rx_throttle.py
async_rx/observable/rx_throw.py
async_rx/observable/rx_window.py
async_rx/observable/rx_zip.py
async_rx/protocol/__init__.py
async_rx/protocol/connectable.py
async_rx/protocol/definition.py
async_rx/protocol/observable.py
async_rx/protocol/observer.py
async_rx/protocol/rx_collector.py
async_rx/protocol/subject.py
async_rx/protocol/subscription.py
async_rx/subject/__init__.py
async_rx/subject/rx_subject.py
async_rx/subject/rx_subject_behavior.py
async_rx/subject/rx_subject_from.py
async_rx/subject/rx_subject_replay.py
async_rx-1.0.4.dist-info/LICENSE.md
async_rx-1.0.4.dist-info/WHEEL
async_rx-1.0.4.dist-info/METADATA
async_rx-1.0.4.dist-info/RECORD
