Metadata-Version: 2.1
Name: async-rx
Version: 1.0.4
Summary: Rx or the observable pattern with curio async.
Home-page: https://pypi.org/project/async_rx
License: MIT
Keywords: async,react,curio,functional,observer,observable
Author: Jerome Guibert
Author-email: jguibert@gmail.com
Requires-Python: >=3.8,<4.0
Classifier: Development Status :: 5 - Production/Stable
Classifier: Intended Audience :: Developers
Classifier: License :: OSI Approved :: MIT License
Classifier: Natural Language :: English
Classifier: Programming Language :: Python
Classifier: Programming Language :: Python :: 3
Classifier: Programming Language :: Python :: 3.8
Classifier: Programming Language :: Python :: 3.9
Classifier: Topic :: Software Development :: Libraries :: Python Modules
Classifier: Typing :: Typed
Requires-Dist: curio (>=1,<2)
Requires-Dist: typing-extensions (>=3.7.4.2,<4.0.0.0); python_version < "3.8"
Project-URL: Documentation, https://geronimo-iia.github.io/async-rx/
Project-URL: Repository, https://github.com/geronimo-iia/async-rx
Project-URL: issues, https://github.com/geronimo-iia/async-rx/issues
